[
  {"id": 1, "minute": 10, "type": {"id": 16, "name": "Shot"}, "player": {"id": 101, "name": "L. Smith"}, "team": {"id": 1, "name": "Home FC"}, "shot": {"outcome": {"id": 97, "name": "Goal"}}},
  {"id": 2, "minute": 12, "type": {"id": 30, "name": "Pass"}, "player": {"id": 101, "name": "L. Smith"}, "team": {"id": 1, "name": "Home FC"}, "pass": {}},
  {"id": 3, "minute": 18, "type": {"id": 30, "name": "Pass"}, "player": {"id": 102, "name": "K. Doe"}, "team": {"id": 1, "name": "Home FC"}, "pass": {"outcome": {"id": 99, "name": "Incomplete"}}},
  {"id": 4, "minute": 25, "type": {"id": 43, "name": "Carry"}, "player": {"id": 101, "name": "L. Smith"}, "team": {"id": 1, "name": "Home FC"}},
  {"id": 5, "minute": 30, "type": {"id": 72, "name": "Pressure"}, "player": {"id": 201, "name": "M. Reyes"}, "team": {"id": 2, "name": "Away United"}},
  {"id": 6, "minute": 35, "type": {"id": 74, "name": "Interception"}, "player": {"id": 201, "name": "M. Reyes"}, "team": {"id": 2, "name": "Away United"}},
  {"id": 7, "minute": 40, "type": {"id": 65, "name": "Duel"}, "player": {"id": 202, "name": "J. Park"}, "team": {"id": 2, "name": "Away United"}},
  {"id": 8, "minute": 44, "type": {"id": 52, "name": "Foul Committed"}, "player": {"id": 102, "name": "K. Doe"}, "team": {"id": 1, "name": "Home FC"}}
]
